django_eraserhead-0.1.5.dist-info/DESCRIPTION.rst
django_eraserhead-0.1.5.dist-info/METADATA
django_eraserhead-0.1.5.dist-info/RECORD
django_eraserhead-0.1.5.dist-info/WHEEL
django_eraserhead-0.1.5.dist-info/metadata.json
django_eraserhead-0.1.5.dist-info/top_level.txt
eraserhead/__init__.py
eraserhead/apps.py
eraserhead/model_instance_wrapper.py
eraserhead/patch.py
eraserhead/queryset_storage.py
eraserhead/request_storage.py
