Metadata-Version: 2.0
Name: django-eraserhead
Version: 0.1.5
Summary: Provide hints to optimize database usage by deferring unused fields
Home-page: https://github.com/dizballanze/django-eraserhead
Author: Iurii Shikanov
Author-email: dizballanze@gmail.com
License: MIT
Keywords: django-eraserhead
Platform: UNKNOWN
Classifier: Development Status :: 3 - Alpha
Classifier: Framework :: Django
Classifier: Framework :: Django :: 1.8
Classifier: Framework :: Django :: 1.9
Classifier: Framework :: Django :: 1.10
Classifier: Framework :: Django :: 1.11
Classifier: Intended Audience :: Developers
Classifier: License :: OSI Approved :: BSD License
Classifier: Natural Language :: English
Classifier: Programming Language :: Python :: 2
Classifier: Programming Language :: Python :: 2.7
Classifier: Programming Language :: Python :: 3
Classifier: Programming Language :: Python :: 3.4
Classifier: Programming Language :: Python :: 3.5
Classifier: Programming Language :: Python :: 3.6
Requires-Dist: funcy (==1.8)
Requires-Dist: humanfriendly (==4.4)
Requires-Dist: py-term (==0.6)
Requires-Dist: wrapt (==1.10.10)
